Metadata-Version: 2.1
Name: irun
Version: 0.2
Summary: High level query language for Reiz
Home-page: https://github.com/reizio/irun
Author: isidentical
Author-email: isidentical@gmail.com
License: UNKNOWN
Platform: UNKNOWN
Classifier: Programming Language :: Python :: 3
Classifier: Programming Language :: Python :: 3 :: Only
Classifier: Programming Language :: Python :: 3.8
Requires-Python: >=3.8
